picorv32_test/src/qspi_serializer.v
module qspi_serializer(
     input clk_i
    ,input rst_i

    ,input        start
    ,output reg   busy

    // group: command
    ,input [7 :0] cmd
    ,input [31:0] addr
    ,input [31:0] alterbytes
    ,input [1:0]  cmd_mode
    ,input [1:0]  addr_mode
    ,input [1:0]  addr_size
    ,input [1:0]  ab_mode
    ,input [1:0]  ab_size
    ,input [1:0]  data_mode
    ,input [1:0]  data_size
    ,input [4:0]  dummy_cycles

    // group: data
    ,input             wr           // read & write. static
    ,input             en_write     // load [data_in] and read [data_out]  @posedge 
    ,output reg        dataready    // seq data send ok or ready tobe read
    ,input      [31:0] data_in
    ,output reg [31:0] data_out
    
    ,inout [3:0]  q_o
    ,output reg   sclk
    ,output reg   csn
);
/********************************************************************************************************************************
state machine
********************************************************************************************************************************/
localparam S_IDLE   = 3'd0;
localparam S_SWICH  = 3'd1;
localparam S_CMD    = 3'd2;
localparam S_ADDR   = 3'd3;
localparam S_ALBT   = 3'd4;
localparam S_DUMM   = 3'd5;
localparam S_DATA   = 3'd6;
localparam S_Wait   = 3'd7;


localparam M_SSPI   = 2'b01;
localparam M_DSPI   = 2'b10;
localparam M_QSPI   = 2'b11;

reg [2:0] curr_state;
reg [2:0] next_state;
reg [2:0] reco_state;


wire __no_cmd  = (cmd_mode     == 2'h0);
wire __no_addr = (addr_mode    == 2'h0);
wire __no_altb = (ab_mode      == 2'h0);
wire __no_dumm = (dummy_cycles == 5'h0);
wire __no_data = (data_mode    == 2'h0);

wire [2:0] __next_state_should_be = 
    (reco_state < S_CMD  && ~__no_cmd )                  ? S_CMD  :
    (reco_state < S_ADDR && ~__no_addr)                  ? S_ADDR :
    (reco_state < S_ALBT && ~__no_altb)                  ? S_ALBT :
    (reco_state < S_DUMM && ~__no_dumm)                  ? S_DUMM :
    (start == 1'b0 || __no_data) ? S_IDLE : (  // S_DATA
        (wr) ? (
            next_wdata_ready ? S_DATA : S_Wait
        ) : (
            next_wdata_ready ? S_Wait : S_DATA
        )
    );

/********************************************************************************************************************************
data control
if [wr == 1]:
    posedge [en_write] : load write data. [next_wdata_ready == 1]
else:
    drive[dataready == 1] : 
********************************************************************************************************************************/
reg next_wdata_ready;
reg [31:0] data_write;
reg data_has_write;

always@ (posedge clk_i or posedge rst_i) begin
    if (rst_i) begin
        data_write <= 32'b0;
        next_wdata_ready <= 1'b0;
    end else begin
        if (curr_state == S_IDLE) begin
            next_wdata_ready <= 1'b0;
        end else if (wr) begin
            if (en_write) begin
                next_wdata_ready <= 1'b1;
                data_write <= data_in;
            end else if (data_has_write == 1'b1) begin
                next_wdata_ready <= 1'b0;
            end
        end else begin
            if (en_write) begin
                next_wdata_ready <= 1'b0;
            end else if(data_has_write) begin
                next_wdata_ready <= 1'b1;
            end
        end
    end
end

        
            
/********************************************************************************************************************************
mode :
    00: none
    01: single
    10: dual
    11: quad
size :
    00: 8bit
    01: 16
    10: 24
    11: 32

cycles = 
    ((size + 1) << 3) >> (mode - 1) = 
    (size + 1) << (4 - mode)

wire [2:0] sz = size + 1;
wire [5:0] cycles = 
    (mode == 2'b11) ? {2'b0 , sz , 1'b0} :
    (mode == 2'b10) ? {1'b0 , sz , 2'b0} :
    (mode == 2'b01) ? {       sz , 3'b0} :
********************************************************************************************************************************/

wire [2:0] __asize = {1'b0, addr_size} + 3'b1;
wire [2:0] __bsize = {1'b0, ab_size  } + 3'b1;
wire [2:0] __dsize = {1'b0, data_size} + 3'b1;

wire [4:0] __cmd_cycles = 
    (cmd_mode  == 2'b11) ? 4'd2 :
    (cmd_mode  == 2'b10) ? 4'd4 :
                           4'd8 ;

wire [5:0] __addr_cycles = 
    (addr_mode == 2'b11) ? {2'b0 , __asize , 1'b0} :
    (addr_mode == 2'b10) ? {1'b0 , __asize , 2'b0} :
                           {       __asize , 3'b0} ;

wire [5:0] __alby_cycles = 
    (ab_mode   == 2'b11) ? {2'b0 , __bsize , 1'b0} :
    (ab_mode   == 2'b10) ? {1'b0 , __bsize , 2'b0} :
                           {       __bsize , 3'b0} ;

wire [5:0] __data_cycles = // per bytes
    (data_mode == 2'b11) ? {2'b0 , __dsize , 1'b0} :
    (data_mode == 2'b10) ? {1'b0 , __dsize , 2'b0} :
                           {       __dsize , 3'b0} ;

/********************************************************************************************************************************
qspi io
********************************************************************************************************************************/
wire [3:0] q_dir_out = 
    (
        ((curr_state == S_DATA) && (wr == 1'b0)) ||
          curr_state == S_DUMM ||
          curr_state == S_Wait ||
          curr_state == S_SWICH
    ) ? 4'h0 : // read data.
    (cur_mode == M_SSPI) ? 4'b0001 :
    (cur_mode == M_DSPI) ? 4'b0011 :
    (cur_mode == M_QSPI) ? 4'b1111 :
    4'h0;
reg [3:0] q_odata;

genvar i;
generate
    for (i=0; i < 4; i=i+1 ) begin:hist
        assign q_o[i] = (q_dir_out[i]) ? q_odata[i]: 1'hz;
    end
endgenerate

// assign q_o = (q_dir_out) ? q_odata: 4'hz;
wire[3:0] q_idata = q_o;

reg  [6:0] bit_cnt;
wire [5:0] bit_len = bit_cnt[6:1];

reg [31:0] cur_byte;
reg [1 :0] cur_size;
reg [1 :0] cur_mode;

always @(posedge clk_i or posedge rst_i) begin
    if (rst_i) begin
        curr_state <= S_IDLE;
    end else begin
        curr_state <= next_state;
    end
end

always@ (negedge clk_i or posedge rst_i) begin
    if (rst_i) begin
        next_state     <= S_IDLE;
        reco_state     <= S_IDLE;
        data_has_write <= 1'b0;
        busy           <= 1'b0;
        dataready      <= 1'b0;
    end else begin
        case (curr_state)
            S_IDLE: begin
                if (start) begin
                    reco_state <= S_IDLE;
                    next_state <= S_SWICH;
                end 
                dataready <= 1'b0;
            end

            S_SWICH: begin
                busy       <= 1'b0;
                dataready  <= 1'b0;
                next_state <= __next_state_should_be;
                case (__next_state_should_be) 
                    S_CMD: begin
                        cur_byte <= {24'b0, cmd};
                        cur_size <= 2'b1;
                        cur_mode <= cmd_mode;
                    end
                    S_ADDR: begin
                        cur_byte <= addr;
                        cur_size <= __asize[1:0];
                        cur_mode <= addr_mode;
                    end
                    S_ALBT: begin
                        cur_byte <= alterbytes;
                        cur_size <= __bsize[1:0];
                        cur_mode <= ab_mode;
                    end
                    S_DATA: begin
                        cur_byte <= data_write;
                        cur_size <= __dsize[1:0];
                        cur_mode <= data_mode;
                        data_has_write <= 1'b1;
                        busy           <= 1'b1;
                    end

                    S_IDLE: begin
                        dataready <= 1'b1;
                    end
                endcase
            end

            S_CMD: begin
                if (bit_len == {1'b0, __cmd_cycles}) begin
                    reco_state <= S_CMD;
                    next_state <= S_SWICH;
                end
            end

            S_ADDR: begin
                if (bit_len == __addr_cycles) begin
                    reco_state <= S_ADDR;
                    next_state <= S_SWICH;
                end
            end

            S_ALBT: begin
                if (bit_len == __alby_cycles) begin
                    reco_state <= S_ALBT;
                    next_state <= S_SWICH;
                end
            end

            S_DUMM: begin
                if (bit_len == {1'b0, dummy_cycles}) begin
                    reco_state <= S_DUMM;
                    next_state <= S_SWICH;
                end
            end

            S_DATA: begin
                data_has_write <= 1'b0;
                if (bit_len == __data_cycles ) begin // && data exist.
                    reco_state <= S_DATA;
                    next_state <= S_SWICH;
                    dataready <= 1'b1;
                end
            end

            S_Wait: begin
                if (next_wdata_ready == wr) begin
                    reco_state <= S_Wait;
                    next_state <= S_SWICH;
                end else if (start == 1'b0) begin
                    next_state <= S_IDLE;
                end
            end
        endcase
    end
end

always @(posedge clk_i or posedge rst_i) begin
    if (rst_i) begin
        csn <= 1'b1;
    end else begin
        if (next_state != S_IDLE && next_state != S_Wait) begin
            bit_cnt <= bit_cnt + 7'b1;
            sclk <= bit_cnt[0];
        end

        if (     
            next_state == S_CMD        || 
            next_state == S_ADDR       ||
            next_state == S_ALBT       ||
           (next_state == S_DATA && wr)) 
        begin
            case (cur_mode) 
                M_SSPI: begin
                    q_odata <= {3'h0, cur_byte[ {cur_size, 3'b0} -  bit_len[4:0]        - 5'b1     ]};
                end

                M_DSPI: begin
                    q_odata <= {2'h0, cur_byte[ {cur_size, 3'b0} - {bit_len[3:0], 1'b0} - 5'b1 -: 2]};
                end

                M_QSPI: begin
                    q_odata <=        cur_byte[ {cur_size, 3'b0} - {bit_len[2:0], 2'b0} - 5'b1 -: 4];
                end
            endcase
        end

        case (next_state)
            S_IDLE: begin
                bit_cnt <= 7'b0;
                sclk <= 1'b0;
                csn <= 1'b1;
            end

            S_SWICH: begin
                bit_cnt <= 7'b0;
                sclk <= 1'b0;
                csn <= 1'b0;
            end

            S_Wait: begin
                bit_cnt <= 7'b0;
                sclk <= 1'b0;
            end

            S_DUMM: begin
                // let output `z
            end

            S_DATA: begin
                if (~wr) begin // read mode
                    if (bit_cnt[0]) begin
                        case (cur_mode) 
                            M_SSPI: begin
                                data_out <= {data_out[30:0], q_idata[1]};
                            end

                            M_DSPI: begin
                                data_out <= {data_out[29:0], q_idata[1:0]};
                            end

                            M_QSPI: begin
                                data_out <= {data_out[27:0], q_idata};
                            end
                        endcase
                    end
                end
            end
        endcase
    end
end

endmodule

picorv32_test/src/qspi_flash_tester.v
module qspi_flash_tester(
     input             clk
    ,input      [4:0]  keys
    ,output     [5:0]  leds

    ,inout      [3:0]  q_o
    ,output            sclk
    ,output     [1:0]  csn
);

assign csn[1] = 1'b1;
localparam WAIT_CYCLES = 16'd65530;

localparam S_IDLE = 3'h0;
localparam S_READ = 3'h1;
localparam S_WAIT = 3'h2;

localparam S_W_EN1 = 3'h3;
localparam S_W_Era = 3'h4;
localparam S_W_EN2 = 3'h5;
localparam S_W_Prg = 3'h6;
localparam S_W_DIS = 3'h7;

reg[2:0] curr_state;
reg[2:0] next_state;


reg start;
wire busy;
reg [7:0] cmd;
reg en_write;

reg [31:0] wdata;
wire [31:0] rdata;
wire dataready;
reg wr;

reg has_address;
reg has_data;

assign leds = wdata[5:0];

wire rst_n = keys[0];
reg [15:0] cnt;

reg[31:0] adder;

always@(posedge clk or negedge rst_n) begin
    if (~rst_n) begin
        curr_state <= S_IDLE;
    end else begin
        curr_state <= next_state;
    end
end

always@( negedge clk or negedge rst_n ) begin
    if (~rst_n) begin
        next_state <= S_IDLE;
        start      <= 1'b0;
        wdata      <= 32'b0;
        adder      <= 32'b0;
    end else begin
        case (curr_state)
            S_IDLE: begin
                if (cnt == 16'd200) begin
                    next_state <= S_READ;
                    start      <= 1'b1;
                end
            end

            S_READ: begin
                if (dataready) begin
                    wdata      <= rdata;
                    start      <= 1'b0;
                    next_state <= S_WAIT;
                    adder      <= rdata;
                end
            end

            S_WAIT: begin
                case(~keys[4:1])
                    4'b0001: begin
                        adder <= 32'hffffffff + wdata; 
                    end

                    4'b0010: begin
                        adder <= 32'h1        + wdata; 
                    end

                    4'b0100: begin
                        next_state <= S_READ;
                        start      <= 1'b1;
                    end

                    4'b1000: begin
                        next_state <= S_W_EN1;
                        start      <= 1'b1;
                    end
                    default: begin
                        wdata <= adder;
                    end
                endcase
                
            end

            S_W_EN1: begin
                if (dataready) begin
                    start <= 1'b0;
                end  
                if (cnt == WAIT_CYCLES) begin
                    next_state <= S_W_Era;
                    start      <= 1'b1;
                end
            end

            S_W_Era: begin
                // erase sector (4k)
                if (dataready) begin
                    start <= 1'b0;
                end  
                if (cnt == WAIT_CYCLES) begin
                    next_state <= S_W_EN2;
                    start      <= 1'b1;
                end
            end

            S_W_EN2: begin
                if (dataready) begin
                    start <= 1'b0;
                end  
                if (cnt == WAIT_CYCLES) begin
                    next_state <= S_W_Prg;
                    start      <= 1'b1;
                end
            end

            S_W_Prg: begin
                if (dataready) begin
                    start <= 1'b0;
                end  
                if (cnt == WAIT_CYCLES) begin
                    next_state <= S_W_DIS;
                    start      <= 1'b1;
                end
            end

            S_W_DIS: begin
                if (dataready) begin
                    start <= 1'b0;
                end  
                if (cnt == WAIT_CYCLES) begin
                    next_state <= S_WAIT;
                end
            end
        endcase
    end
end

always@(posedge clk or negedge rst_n)begin
    if (~rst_n) begin
        cnt <= 16'b0;
        en_write <= 1'b0;
    end else begin
        case (next_state) 
            S_IDLE: begin
                cnt <= cnt + 16'b1;
            end
            S_READ: begin
                wr          <= 1'b0;
                cmd         <= 8'h03;
                has_address <= 1'b1;
                has_data    <= 1'b1;
            end

            S_WAIT: begin
                
            end

            S_W_EN1: begin
                cmd <= 8'h06;
                has_address <= 1'b0;
                has_data <= 1'b0;
                if (csn[0] == 1'b1) begin
                    cnt <= cnt + 16'b1;
                end else begin
                    cnt <= 16'b0;
                end
            end

            S_W_Era: begin
                cmd <= 8'h20;
                has_address <= 1'b1;
                has_data <= 1'b0;
                if (csn[0] == 1'b1) begin
                    cnt <= cnt + 16'b1;
                end else begin
                    cnt <= 16'b0;
                end
            end

            S_W_EN2: begin
                cmd <= 8'h06;
                has_address <= 1'b0;
                has_data <= 1'b0;
                if (csn[0] == 1'b1) begin
                    cnt <= cnt + 16'b1;
                end else begin
                    cnt <= 16'b0;
                end
            end

            S_W_Prg: begin
                cmd <= 8'h02;
                has_address <= 1'b1;
                has_data <= 1'b1;
                wr <= 1'b1;
                if (~busy && ~csn[0]) begin
                    en_write <= 1'b1;
                end else begin
                    en_write <= 1'b0;
                end
                if (csn[0] == 1'b1) begin
                    cnt <= cnt + 16'b1;
                end else begin
                    cnt <= 16'b0;
                end
            end

            S_W_DIS: begin
                cmd <= 8'h04; // TOOO: fix code
                has_address <= 1'b0;
                has_data <= 1'b0;
                wr <= 1'b0;
                cnt <= 16'b0;
            end

        endcase
    end
end


qspi_serializer qspis(
    .clk_i(~clk),
    .rst_i(~rst_n),

    .start(start),
    .busy(busy),

    .cmd(cmd),
    .cmd_mode(2'b01),

    .addr(32'b0),
    .addr_size(2'b10),
    .addr_mode(has_address ? 2'b01 : 2'b00),

    .alterbytes(32'h00),
    .ab_size(2'b00),
    .ab_mode(2'b00),

    .dummy_cycles(5'd0),
    
    .data_size(2'b00),
    .data_mode(has_data ? 2'b01 : 2'b0),

    .data_in(wdata),
    .data_out(rdata),
    .wr(wr),
    .en_write(en_write),
    .dataready(dataready),
    .q_o(q_o),
    .sclk(sclk),
    .csn(csn[0])
);



endmodule

picorv32_test/tb/tb.v
`timescale 1ns/1ns
module tb;

reg clk;

reg [4:0] keys;
wire [5:0] leds;

initial begin
    keys = 4'b0;

    #1 keys[0] = 1'b1;
    #16 keys[0] = 1'b0;


    #8000 keys[4] = 1'b1;
    #11   keys[4] = 1'b0;


    // #50 keys[4] = 1'b1;
    // #10 keys[4] = 1'b0;

end


initial begin
    $dumpvars(0, tb);
    $dumpfile("ok.vvp");
    
    clk = 1'b0;

    #50000 $finish;
end

always #5 begin
    clk = ~clk;
end

wire [3:0] q_o;

reg [31:0] wdata;
wire [31:0] rdata;

qspi_flash_tester qtester(
    .clk(clk),
    .keys(~keys),
    .leds(leds)

);

/*
keys[4:0]:
    [4]: write
    [3]: read
    [2]: add
    [1]: sub


*/





endmodule

picorv32_test/tb/dump.vcd
$date
	Fri Mar 10 03:13:21 2023
$end
$version
	Icarus Verilog
$end
$timescale
	1ns
$end
$scope module tb $end
$var wire 6 ! leds [5:0] $end
$var reg 1 " clk $end
$var reg 5 # keys [4:0] $end
$scope module qtester $end
$var wire 1 " clk $end
$var wire 5 $ keys [4:0] $end
$var wire 1 % sclk $end
$var wire 1 & rst_n $end
$var wire 32 ' rdata [31:0] $end
$var wire 4 ( q_o [3:0] $end
$var wire 6 ) leds [5:0] $end
$var wire 1 * dataready $end
$var wire 2 + csn [1:0] $end
$var wire 1 , busy $end
$var parameter 3 - S_IDLE $end
$var parameter 3 . S_READ $end
$var parameter 3 / S_WAIT $end
$var parameter 3 0 S_W_DIS $end
$var parameter 3 1 S_W_EN1 $end
$var parameter 3 2 S_W_EN2 $end
$var parameter 3 3 S_W_Era $end
$var parameter 3 4 S_W_Prg $end
$var parameter 16 5 WAIT_CYCLES $end
$var reg 32 6 adder [31:0] $end
$var reg 8 7 cmd [7:0] $end
$var reg 16 8 cnt [15:0] $end
$var reg 3 9 curr_state [2:0] $end
$var reg 1 : en_write $end
$var reg 1 ; has_address $end
$var reg 1 < has_data $end
$var reg 3 = next_state [2:0] $end
$var reg 1 > start $end
$var reg 32 ? wdata [31:0] $end
$var reg 1 @ wr $end
$scope module qspis $end
$var wire 2 A ab_mode [1:0] $end
$var wire 2 B ab_size [1:0] $end
$var wire 32 C addr [31:0] $end
$var wire 2 D addr_mode [1:0] $end
$var wire 2 E addr_size [1:0] $end
$var wire 32 F alterbytes [31:0] $end
$var wire 1 G clk_i $end
$var wire 8 H cmd [7:0] $end
$var wire 2 I cmd_mode [1:0] $end
$var wire 32 J data_in [31:0] $end
$var wire 2 K data_mode [1:0] $end
$var wire 2 L data_size [1:0] $end
$var wire 5 M dummy_cycles [4:0] $end
$var wire 1 : en_write $end
$var wire 4 N q_idata [3:0] $end
$var wire 1 O rst_i $end
$var wire 1 > start $end
$var wire 1 @ wr $end
$var wire 4 P q_o [3:0] $end
$var wire 4 Q q_dir_out [3:0] $end
$var wire 6 R bit_len [5:0] $end
$var wire 1 S __no_dumm $end
$var wire 1 T __no_data $end
$var wire 1 U __no_cmd $end
$var wire 1 V __no_altb $end
$var wire 1 W __no_addr $end
$var wire 3 X __next_state_should_be [2:0] $end
$var wire 3 Y __dsize [2:0] $end
$var wire 6 Z __data_cycles [5:0] $end
$var wire 5 [ __cmd_cycles [4:0] $end
$var wire 3 \ __bsize [2:0] $end
$var wire 3 ] __asize [2:0] $end
$var wire 6 ^ __alby_cycles [5:0] $end
$var wire 6 _ __addr_cycles [5:0] $end
$var parameter 2 ` M_DSPI $end
$var parameter 2 a M_QSPI $end
$var parameter 2 b M_SSPI $end
$var parameter 3 c S_ADDR $end
$var parameter 3 d S_ALBT $end
$var parameter 3 e S_CMD $end
$var parameter 3 f S_DATA $end
$var parameter 3 g S_DUMM $end
$var parameter 3 h S_IDLE $end
$var parameter 3 i S_SWICH $end
$var parameter 3 j S_Wait $end
$var reg 7 k bit_cnt [6:0] $end
$var reg 1 , busy $end
$var reg 1 l csn $end
$var reg 32 m cur_byte [31:0] $end
$var reg 2 n cur_mode [1:0] $end
$var reg 2 o cur_size [1:0] $end
$var reg 3 p curr_state [2:0] $end
$var reg 1 q data_has_write $end
$var reg 32 r data_out [31:0] $end
$var reg 32 s data_write [31:0] $end
$var reg 1 * dataready $end
$var reg 3 t next_state [2:0] $end
$var reg 1 u next_wdata_ready $end
$var reg 4 v q_odata [3:0] $end
$var reg 3 w reco_state [2:0] $end
$var reg 1 % sclk $end
$scope begin hist[0] $end
$var parameter 2 x i $end
$upscope $end
$scope begin hist[1] $end
$var parameter 2 y i $end
$upscope $end
$scope begin hist[2] $end
$var parameter 3 z i $end
$upscope $end
$scope begin hist[3] $end
$var parameter 3 { i $end
$upscope $end
$upscope $end
$upscope $end
$upscope $end
$enddefinitions $end
$comment Show the parameter values. $end
$dumpall
b11 {
b10 z
b1 y
b0 x
b111 j
b1 i
b0 h
b101 g
b110 f
b10 e
b100 d
b11 c
b1 b
b11 a
b10 `
b1111111111111010 5
b110 4
b100 3
b101 2
b11 1
b111 0
b10 /
b1 .
b0 -
$end
#0
$dumpvars
bx w
bx v
xu
bx t
bx s
bx r
xq
bx p
bx o
bx n
bx m
xl
bx k
b11000 _
b1000 ^
b11 ]
b1 \
b1000 [
b1000 Z
b1 Y
bx X
xW
1V
0U
xT
1S
bx R
bx Q
bx P
0O
bx N
b0 M
b0 L
b0x K
bx J
b1 I
bx H
1G
b0 F
b10 E
b0x D
b0 C
b0 B
b0 A
x@
bx ?
x>
bx =
x<
x;
x:
bx 9
bx 8
bx 7
bx 6
x,
b1x +
x*
bx )
bx (
bx '
1&
x%
b11111 $
b0 #
0"
bx !
$end
#1
b10 X
b0 !
b0 )
b11 +
1l
b0 p
0u
b0 s
0*
0,
0q
b0 w
b0 t
b0 9
0:
b0 8
b0 6
b0 ?
b0 J
0>
b0 =
1O
0&
b11110 $
b1 #
#5
0G
1"
#10
1G
0"
#15
0G
1"
#17
0O
1&
b11111 $
b0 #
#20
b0 R
0%
b0 k
1G
0"
#25
b1 8
0G
1"
#30
1G
0"
#35
b10 8
0G
1"
#40
1G
0"
#45
b11 8
0G
1"
#50
1G
0"
#55
b100 8
0G
1"
#60
1G
0"
#65
b101 8
0G
1"
#70
1G
0"
#75
b110 8
0G
1"
#80
1G
0"
#85
b111 8
0G
1"
#90
1G
0"
#95
b1000 8
0G
1"
#100
1G
0"
#105
b1001 8
0G
1"
#110
1G
0"
#115
b1010 8
0G
1"
#120
1G
0"
#125
b1011 8
0G
1"
#130
1G
0"
#135
b1100 8
0G
1"
#140
1G
0"
#145
b1101 8
0G
1"
#150
1G
0"
#155
b1110 8
0G
1"
#160
1G
0"
#165
b1111 8
0G
1"
#170
1G
0"
#175
b10000 8
0G
1"
#180
1G
0"
#185
b10001 8
0G
1"
#190
1G
0"
#195
b10010 8
0G
1"
#200
1G
0"
#205
b10011 8
0G
1"
#210
1G
0"
#215
b10100 8
0G
1"
#220
1G
0"
#225
b10101 8
0G
1"
#230
1G
0"
#235
b10110 8
0G
1"
#240
1G
0"
#245
b10111 8
0G
1"
#250
1G
0"
#255
b11000 8
0G
1"
#260
1G
0"
#265
b11001 8
0G
1"
#270
1G
0"
#275
b11010 8
0G
1"
#280
1G
0"
#285
b11011 8
0G
1"
#290
1G
0"
#295
b11100 8
0G
1"
#300
1G
0"
#305
b11101 8
0G
1"
#310
1G
0"
#315
b11110 8
0G
1"
#320
1G
0"
#325
b11111 8
0G
1"
#330
1G
0"
#335
b100000 8
0G
1"
#340
1G
0"
#345
b100001 8
0G
1"
#350
1G
0"
#355
b100010 8
0G
1"
#360
1G
0"
#365
b100011 8
0G
1"
#370
1G
0"
#375
b100100 8
0G
1"
#380
1G
0"
#385
b100101 8
0G
1"
#390
1G
0"
#395
b100110 8
0G
1"
#400
1G
0"
#405
b100111 8
0G
1"
#410
1G
0"
#415
b101000 8
0G
1"
#420
1G
0"
#425
b101001 8
0G
1"
#430
1G
0"
#435
b101010 8
0G
1"
#440
1G
0"
#445
b101011 8
0G
1"
#450
1G
0"
#455
b101100 8
0G
1"
#460
1G
0"
#465
b101101 8
0G
1"
#470
1G
0"
#475
b101110 8
0G
1"
#480
1G
0"
#485
b101111 8
0G
1"
#490
1G
0"
#495
b110000 8
0G
1"
#500
1G
0"
#505
b110001 8
0G
1"
#510
1G
0"
#515
b110010 8
0G
1"
#520
1G
0"
#525
b110011 8
0G
1"
#530
1G
0"
#535
b110100 8
0G
1"
#540
1G
0"
#545
b110101 8
0G
1"
#550
1G
0"
#555
b110110 8
0G
1"
#560
1G
0"
#565
b110111 8
0G
1"
#570
1G
0"
#575
b111000 8
0G
1"
#580
1G
0"
#585
b111001 8
0G
1"
#590
1G
0"
#595
b111010 8
0G
1"
#600
1G
0"
#605
b111011 8
0G
1"
#610
1G
0"
#615
b111100 8
0G
1"
#620
1G
0"
#625
b111101 8
0G
1"
#630
1G
0"
#635
b111110 8
0G
1"
#640
1G
0"
#645
b111111 8
0G
1"
#650
1G
0"
#655
b1000000 8
0G
1"
#660
1G
0"
#665
b1000001 8
0G
1"
#670
1G
0"
#675
b1000010 8
0G
1"
#680
1G
0"
#685
b1000011 8
0G
1"
#690
1G
0"
#695
b1000100 8
0G
1"
#700
1G
0"
#705
b1000101 8
0G
1"
#710
1G
0"
#715
b1000110 8
0G
1"
#720
1G
0"
#725
b1000111 8
0G
1"
#730
1G
0"
#735
b1001000 8
0G
1"
#740
1G
0"
#745
b1001001 8
0G
1"
#750
1G
0"
#755
b1001010 8
0G
1"
#760
1G
0"
#765
b1001011 8
0G
1"
#770
1G
0"
#775
b1001100 8
0G
1"
#780
1G
0"
#785
b1001101 8
0G
1"
#790
1G
0"
#795
b1001110 8
0G
1"
#800
1G
0"
#805
b1001111 8
0G
1"
#810
1G
0"
#815
b1010000 8
0G
1"
#820
1G
0"
#825
b1010001 8
0G
1"
#830
1G
0"
#835
b1010010 8
0G
1"
#840
1G
0"
#845
b1010011 8
0G
1"
#850
1G
0"
#855
b1010100 8
0G
1"
#860
1G
0"
#865
b1010101 8
0G
1"
#870
1G
0"
#875
b1010110 8
0G
1"
#880
1G
0"
#885
b1010111 8
0G
1"
#890
1G
0"
#895
b1011000 8
0G
1"
#900
1G
0"
#905
b1011001 8
0G
1"
#910
1G
0"
#915
b1011010 8
0G
1"
#920
1G
0"
#925
b1011011 8
0G
1"
#930
1G
0"
#935
b1011100 8
0G
1"
#940
1G
0"
#945
b1011101 8
0G
1"
#950
1G
0"
#955
b1011110 8
0G
1"
#960
1G
0"
#965
b1011111 8
0G
1"
#970
1G
0"
#975
b1100000 8
0G
1"
#980
1G
0"
#985
b1100001 8
0G
1"
#990
1G
0"
#995
b1100010 8
0G
1"
#1000
1G
0"
#1005
b1100011 8
0G
1"
#1010
1G
0"
#1015
b1100100 8
0G
1"
#1020
1G
0"
#1025
b1100101 8
0G
1"
#1030
1G
0"
#1035
b1100110 8
0G
1"
#1040
1G
0"
#1045
b1100111 8
0G
1"
#1050
1G
0"
#1055
b1101000 8
0G
1"
#1060
1G
0"
#1065
b1101001 8
0G
1"
#1070
1G
0"
#1075
b1101010 8
0G
1"
#1080
1G
0"
#1085
b1101011 8
0G
1"
#1090
1G
0"
#1095
b1101100 8
0G
1"
#1100
1G
0"
#1105
b1101101 8
0G
1"
#1110
1G
0"
#1115
b1101110 8
0G
1"
#1120
1G
0"
#1125
b1101111 8
0G
1"
#1130
1G
0"
#1135
b1110000 8
0G
1"
#1140
1G
0"
#1145
b1110001 8
0G
1"
#1150
1G
0"
#1155
b1110010 8
0G
1"
#1160
1G
0"
#1165
b1110011 8
0G
1"
#1170
1G
0"
#1175
b1110100 8
0G
1"
#1180
1G
0"
#1185
b1110101 8
0G
1"
#1190
1G
0"
#1195
b1110110 8
0G
1"
#1200
1G
0"
#1205
b1110111 8
0G
1"
#1210
1G
0"
#1215
b1111000 8
0G
1"
#1220
1G
0"
#1225
b1111001 8
0G
1"
#1230
1G
0"
#1235
b1111010 8
0G
1"
#1240
1G
0"
#1245
b1111011 8
0G
1"
#1250
1G
0"
#1255
b1111100 8
0G
1"
#1260
1G
0"
#1265
b1111101 8
0G
1"
#1270
1G
0"
#1275
b1111110 8
0G
1"
#1280
1G
0"
#1285
b1111111 8
0G
1"
#1290
1G
0"
#1295
b10000000 8
0G
1"
#1300
1G
0"
#1305
b10000001 8
0G
1"
#1310
1G
0"
#1315
b10000010 8
0G
1"
#1320
1G
0"
#1325
b10000011 8
0G
1"
#1330
1G
0"
#1335
b10000100 8
0G
1"
#1340
1G
0"
#1345
b10000101 8
0G
1"
#1350
1G
0"
#1355
b10000110 8
0G
1"
#1360
1G
0"
#1365
b10000111 8
0G
1"
#1370
1G
0"
#1375
b10001000 8
0G
1"
#1380
1G
0"
#1385
b10001001 8
0G
1"
#1390
1G
0"
#1395
b10001010 8
0G
1"
#1400
1G
0"
#1405
b10001011 8
0G
1"
#1410
1G
0"
#1415
b10001100 8
0G
1"
#1420
1G
0"
#1425
b10001101 8
0G
1"
#1430
1G
0"
#1435
b10001110 8
0G
1"
#1440
1G
0"
#1445
b10001111 8
0G
1"
#1450
1G
0"
#1455
b10010000 8
0G
1"
#1460
1G
0"
#1465
b10010001 8
0G
1"
#1470
1G
0"
#1475
b10010010 8
0G
1"
#1480
1G
0"
#1485
b10010011 8
0G
1"
#1490
1G
0"
#1495
b10010100 8
0G
1"
#1500
1G
0"
#1505
b10010101 8
0G
1"
#1510
1G
0"
#1515
b10010110 8
0G
1"
#1520
1G
0"
#1525
b10010111 8
0G
1"
#1530
1G
0"
#1535
b10011000 8
0G
1"
#1540
1G
0"
#1545
b10011001 8
0G
1"
#1550
1G
0"
#1555
b10011010 8
0G
1"
#1560
1G
0"
#1565
b10011011 8
0G
1"
#1570
1G
0"
#1575
b10011100 8
0G
1"
#1580
1G
0"
#1585
b10011101 8
0G
1"
#1590
1G
0"
#1595
b10011110 8
0G
1"
#1600
1G
0"
#1605
b10011111 8
0G
1"
#1610
1G
0"
#1615
b10100000 8
0G
1"
#1620
1G
0"
#1625
b10100001 8
0G
1"
#1630
1G
0"
#1635
b10100010 8
0G
1"
#1640
1G
0"
#1645
b10100011 8
0G
1"
#1650
1G
0"
#1655
b10100100 8
0G
1"
#1660
1G
0"
#1665
b10100101 8
0G
1"
#1670
1G
0"
#1675
b10100110 8
0G
1"
#1680
1G
0"
#1685
b10100111 8
0G
1"
#1690
1G
0"
#1695
b10101000 8
0G
1"
#1700
1G
0"
#1705
b10101001 8
0G
1"
#1710
1G
0"
#1715
b10101010 8
0G
1"
#1720
1G
0"
#1725
b10101011 8
0G
1"
#1730
1G
0"
#1735
b10101100 8
0G
1"
#1740
1G
0"
#1745
b10101101 8
0G
1"
#1750
1G
0"
#1755
b10101110 8
0G
1"
#1760
1G
0"
#1765
b10101111 8
0G
1"
#1770
1G
0"
#1775
b10110000 8
0G
1"
#1780
1G
0"
#1785
b10110001 8
0G
1"
#1790
1G
0"
#1795
b10110010 8
0G
1"
#1800
1G
0"
#1805
b10110011 8
0G
1"
#1810
1G
0"
#1815
b10110100 8
0G
1"
#1820
1G
0"
#1825
b10110101 8
0G
1"
#1830
1G
0"
#1835
b10110110 8
0G
1"
#1840
1G
0"
#1845
b10110111 8
0G
1"
#1850
1G
0"
#1855
b10111000 8
0G
1"
#1860
1G
0"
#1865
b10111001 8
0G
1"
#1870
1G
0"
#1875
b10111010 8
0G
1"
#1880
1G
0"
#1885
b10111011 8
0G
1"
#1890
1G
0"
#1895
b10111100 8
0G
1"
#1900
1G
0"
#1905
b10111101 8
0G
1"
#1910
1G
0"
#1915
b10111110 8
0G
1"
#1920
1G
0"
